marshmallow_meta/__init__.py
marshmallow_meta-0.0.1.dist-info/LICENSE
marshmallow_meta-0.0.1.dist-info/METADATA
marshmallow_meta-0.0.1.dist-info/WHEEL
marshmallow_meta-0.0.1.dist-info/top_level.txt
marshmallow_meta-0.0.1.dist-info/RECORD
