Metadata-Version: 2.1
Name: marshmallow-meta
Version: 0.0.1
Summary: decorator syntax for marshmallow meta attributes (with inheritance)
Home-page: https://github.com/deckar01/marshmallow-meta
Author: Jared Deckard
Author-email: jared@shademaps.com
Project-URL: Bug Tracker, https://github.com/pypa/deckar01/marshmallow-meta/issues
Classifier: Programming Language :: Python :: 3
Classifier: License :: OSI Approved :: MIT License
Classifier: Operating System :: OS Independent
Requires-Python: >=3.6
License-File: LICENSE
